[{"entity": "Home", "entity_type": "page", "event": "page_dom_modified", "action": "DOM edited", "timestamp": "2025-02-01T12:46:41.650Z", "user": "Sean Connelly", "report": "reports/2025-W05_2025-01-27_2025-02-02.html", "period": "Jan 27 \u2013 Feb 2, 2025", "week": "2025-W05"}, {"entity": "Referral Program", "entity_type": "page", "event": "page_dom_modified", "action": "DOM edited", "timestamp": "2025-01-31T21:15:59.135Z", "user": "Sean Connelly", "report": "reports/2025-W05_2025-01-27_2025-02-02.html", "period": "Jan 27 \u2013 Feb 2, 2025", "week": "2025-W05"}, {"entity": "Referral Terms & Conditions", "entity_type": "page", "event": "page_dom_modified", "action": "DOM edited", "timestamp": "2025-01-31T21:03:25.243Z", "user": "Sean Connelly", "report": "reports/2025-W05_2025-01-27_2025-02-02.html", "period": "Jan 27 \u2013 Feb 2, 2025", "week": "2025-W05"}, {"entity": "Referral Terms & Conditions", "entity_type": "page", "event": "page_dom_modified", "action": "DOM edited", "timestamp": "2025-01-31T20:59:37.151Z", "user": "Sean Connelly", "report": "reports/2025-W05_2025-01-27_2025-02-02.html", "period": "Jan 27 \u2013 Feb 2, 2025", "week": "2025-W05"}, {"entity": "Referral Terms & Conditions", "entity_type": "page", "event": "page_dom_modified", "action": "DOM edited", "timestamp": "2025-01-31T20:46:22.453Z", "user": "Sean Connelly", "report": "reports/2025-W05_2025-01-27_2025-02-02.html", "period": "Jan 27 \u2013 Feb 2, 2025", "week": "2025-W05"}, {"entity": "SureHR", "entity_type": "page", "event": "page_dom_modified", "action": "DOM edited", "timestamp": "2025-01-31T20:45:21.199Z", "user": "Michael Rosenthal", "report": "reports/2025-W05_2025-01-27_2025-02-02.html", "period": "Jan 27 \u2013 Feb 2, 2025", "week": "2025-W05"}, {"entity": "Referral Terms & Conditions", "entity_type": "page", "event": "page_dom_modified", "action": "DOM edited", "timestamp": "2025-01-31T20:37:06.187Z", "user": "Sean Connelly", "report": "reports/2025-W05_2025-01-27_2025-02-02.html", "period": "Jan 27 \u2013 Feb 2, 2025", "week": "2025-W05"}, {"entity": "Referral Terms & Conditions", "entity_type": "page", "event": "page_dom_modified", "action": "DOM edited", "timestamp": "2025-01-31T20:35:42.590Z", "user": "Sean Connelly", "report": "reports/2025-W05_2025-01-27_2025-02-02.html", "period": "Jan 27 \u2013 Feb 2, 2025", "week": "2025-W05"}, {"entity": "Referral Terms & Conditions", "entity_type": "page", "event": "page_dom_modified", "action": "DOM edited", "timestamp": "2025-01-31T20:27:55.154Z", "user": "Sean Connelly", "report": "reports/2025-W05_2025-01-27_2025-02-02.html", "period": "Jan 27 \u2013 Feb 2, 2025", "week": "2025-W05"}, {"entity": "SureHR", "entity_type": "page", "event": "page_dom_modified", "action": "DOM edited", "timestamp": "2025-01-31T20:26:15.366Z", "user": "Michael Rosenthal", "report": "reports/2025-W05_2025-01-27_2025-02-02.html", "period": "Jan 27 \u2013 Feb 2, 2025", "week": "2025-W05"}, {"entity": "SureHR", "entity_type": "page", "event": "page_dom_modified", "action": "DOM edited", "timestamp": "2025-01-31T20:14:51.729Z", "user": "Michael Rosenthal", "report": "reports/2025-W05_2025-01-27_2025-02-02.html", "period": "Jan 27 \u2013 Feb 2, 2025", "week": "2025-W05"}, {"entity": "Refer a Business and Earn Free Payroll", "entity_type": "page", "event": "page_dom_modified", "action": "DOM edited", "timestamp": "2025-01-31T20:18:46.288Z", "user": "Sean Connelly", "report": "reports/2025-W05_2025-01-27_2025-02-02.html", "period": "Jan 27 \u2013 Feb 2, 2025", "week": "2025-W05"}, {"entity": "Disclaimer", "entity_type": "page", "event": "page_dom_modified", "action": "DOM edited", "timestamp": "2025-01-31T20:15:45.580Z", "user": "Sean Connelly", "report": "reports/2025-W05_2025-01-27_2025-02-02.html", "period": "Jan 27 \u2013 Feb 2, 2025", "week": "2025-W05"}, {"entity": "How Many Pay Periods are in a Year | Payroll Guide", "entity_type": "article", "event": "cms_item", "action": "Modified", "timestamp": "2025-01-31T14:13:20.003Z", "user": "System", "report": "reports/2025-W05_2025-01-27_2025-02-02.html", "period": "Jan 27 \u2013 Feb 2, 2025", "week": "2025-W05"}, {"entity": "How Many Pay Periods are in a Year | Payroll Guide", "entity_type": "article", "event": "cms_item", "action": "Modified", "timestamp": "2025-01-31T14:11:27.989Z", "user": "System", "report": "reports/2025-W05_2025-01-27_2025-02-02.html", "period": "Jan 27 \u2013 Feb 2, 2025", "week": "2025-W05"}, {"entity": "How Many Pay Periods are in a Year | Payroll Guide", "entity_type": "article", "event": "cms_item", "action": "Modified", "timestamp": "2025-01-31T14:08:04.503Z", "user": "System", "report": "reports/2025-W05_2025-01-27_2025-02-02.html", "period": "Jan 27 \u2013 Feb 2, 2025", "week": "2025-W05"}, {"entity": "How Many Pay Periods are in a Year | Payroll Guide", "entity_type": "article", "event": "cms_item", "action": "Modified", "timestamp": "2025-01-31T14:03:57.314Z", "user": "System", "report": "reports/2025-W05_2025-01-27_2025-02-02.html", "period": "Jan 27 \u2013 Feb 2, 2025", "week": "2025-W05"}, {"entity": "Refer a Business and Earn Free Payroll", "entity_type": "page", "event": "page_dom_modified", "action": "DOM edited", "timestamp": "2025-01-31T00:10:11.313Z", "user": "Akimbo Studio", "report": "reports/2025-W05_2025-01-27_2025-02-02.html", "period": "Jan 27 \u2013 Feb 2, 2025", "week": "2025-W05"}, {"entity": "Referral Terms & Conditions", "entity_type": "page", "event": "page_dom_modified", "action": "DOM edited", "timestamp": "2025-01-31T00:08:46.739Z", "user": "Akimbo Studio", "report": "reports/2025-W05_2025-01-27_2025-02-02.html", "period": "Jan 27 \u2013 Feb 2, 2025", "week": "2025-W05"}, {"entity": "Disclaimer", "entity_type": "page", "event": "page_dom_modified", "action": "DOM edited", "timestamp": "2025-01-31T00:05:28.124Z", "user": "Akimbo Studio", "report": "reports/2025-W05_2025-01-27_2025-02-02.html", "period": "Jan 27 \u2013 Feb 2, 2025", "week": "2025-W05"}, {"entity": "Epayroll", "entity_type": "article", "event": "cms_item", "action": "Modified", "timestamp": "2025-01-30T16:48:04.676Z", "user": "Dustin Solmonson", "report": "reports/2025-W05_2025-01-27_2025-02-02.html", "period": "Jan 27 \u2013 Feb 2, 2025", "week": "2025-W05"}, {"entity": "Terminologies Template", "entity_type": "page", "event": "page_dom_modified", "action": "DOM edited", "timestamp": "2025-01-30T16:47:32.650Z", "user": "Dustin Solmonson", "report": "reports/2025-W05_2025-01-27_2025-02-02.html", "period": "Jan 27 \u2013 Feb 2, 2025", "week": "2025-W05"}, {"entity": "Terminologies Template", "entity_type": "page", "event": "page_dom_modified", "action": "DOM edited", "timestamp": "2025-01-30T16:37:43.891Z", "user": "Dustin Solmonson", "report": "reports/2025-W05_2025-01-27_2025-02-02.html", "period": "Jan 27 \u2013 Feb 2, 2025", "week": "2025-W05"}, {"entity": "Articles Template", "entity_type": "page", "event": "page_dom_modified", "action": "DOM edited", "timestamp": "2025-01-30T16:32:58.376Z", "user": "Dustin Solmonson", "report": "reports/2025-W05_2025-01-27_2025-02-02.html", "period": "Jan 27 \u2013 Feb 2, 2025", "week": "2025-W05"}, {"entity": "FORMS WIP Home", "entity_type": "page", "event": "page_dom_modified", "action": "DOM edited", "timestamp": "2025-01-30T14:53:16.856Z", "user": "Marina Gallardo", "report": "reports/2025-W05_2025-01-27_2025-02-02.html", "period": "Jan 27 \u2013 Feb 2, 2025", "week": "2025-W05"}, {"entity": "body", "entity_type": "page", "event": "page_settings_custom_code_modified", "action": "Custom code edited", "timestamp": "2025-01-30T14:15:51.224Z", "user": "Marina Gallardo", "report": "reports/2025-W05_2025-01-27_2025-02-02.html", "period": "Jan 27 \u2013 Feb 2, 2025", "week": "2025-W05"}, {"entity": "body", "entity_type": "page", "event": "page_settings_custom_code_modified", "action": "Custom code edited", "timestamp": "2025-01-30T14:11:54.391Z", "user": "Marina Gallardo", "report": "reports/2025-W05_2025-01-27_2025-02-02.html", "period": "Jan 27 \u2013 Feb 2, 2025", "week": "2025-W05"}, {"entity": "State Reciprocity: When Where You Live Isn\u2019t Where You Work  ", "entity_type": "article", "event": "cms_item", "action": "Modified", "timestamp": "2025-01-30T09:45:28.780Z", "user": "System", "report": "reports/2025-W05_2025-01-27_2025-02-02.html", "period": "Jan 27 \u2013 Feb 2, 2025", "week": "2025-W05"}, {"entity": "Best Small Business Payroll Solutions in 2025 | SurePayroll ", "entity_type": "article", "event": "cms_item", "action": "Modified", "timestamp": "2025-01-29T22:17:41.896Z", "user": "System", "report": "reports/2025-W05_2025-01-27_2025-02-02.html", "period": "Jan 27 \u2013 Feb 2, 2025", "week": "2025-W05"}, {"entity": "Best Small Business Payroll Solutions in 2025 | SurePayroll ", "entity_type": "article", "event": "cms_item", "action": "Modified", "timestamp": "2025-01-29T22:12:00.560Z", "user": "System", "report": "reports/2025-W05_2025-01-27_2025-02-02.html", "period": "Jan 27 \u2013 Feb 2, 2025", "week": "2025-W05"}, {"entity": "Default Payroll vs Auto Payroll: Which is Right for You? ", "entity_type": "article", "event": "cms_item", "action": "Modified", "timestamp": "2025-01-29T22:09:12.581Z", "user": "System", "report": "reports/2025-W05_2025-01-27_2025-02-02.html", "period": "Jan 27 \u2013 Feb 2, 2025", "week": "2025-W05"}, {"entity": "Default Payroll vs Auto Payroll: Which is Right for You? ", "entity_type": "article", "event": "cms_item", "action": "Modified", "timestamp": "2025-01-29T22:06:16.220Z", "user": "System", "report": "reports/2025-W05_2025-01-27_2025-02-02.html", "period": "Jan 27 \u2013 Feb 2, 2025", "week": "2025-W05"}, {"entity": "Referral Terms & Conditions", "entity_type": "page", "event": "page_dom_modified", "action": "DOM edited", "timestamp": "2025-01-29T14:04:01.640Z", "user": "Akimbo Studio", "report": "reports/2025-W05_2025-01-27_2025-02-02.html", "period": "Jan 27 \u2013 Feb 2, 2025", "week": "2025-W05"}, {"entity": "Referral Program", "entity_type": "page", "event": "page_dom_modified", "action": "DOM edited", "timestamp": "2025-01-29T13:51:42.589Z", "user": "Akimbo Studio", "report": "reports/2025-W05_2025-01-27_2025-02-02.html", "period": "Jan 27 \u2013 Feb 2, 2025", "week": "2025-W05"}, {"entity": "Refer a Business and Earn Free Payroll", "entity_type": "page", "event": "page_dom_modified", "action": "DOM edited", "timestamp": "2025-01-29T13:42:45.999Z", "user": "Akimbo Studio", "report": "reports/2025-W05_2025-01-27_2025-02-02.html", "period": "Jan 27 \u2013 Feb 2, 2025", "week": "2025-W05"}, {"entity": "Disclaimer", "entity_type": "page", "event": "page_dom_modified", "action": "DOM edited", "timestamp": "2025-01-29T13:14:04.750Z", "user": "Akimbo Studio", "report": "reports/2025-W05_2025-01-27_2025-02-02.html", "period": "Jan 27 \u2013 Feb 2, 2025", "week": "2025-W05"}, {"entity": "Disclaimer", "entity_type": "page", "event": "page_dom_modified", "action": "DOM edited", "timestamp": "2025-01-29T13:11:47.839Z", "user": "Akimbo Studio", "report": "reports/2025-W05_2025-01-27_2025-02-02.html", "period": "Jan 27 \u2013 Feb 2, 2025", "week": "2025-W05"}, {"entity": "Nannychex is SurePayroll by Paychex", "entity_type": "page", "event": "page_dom_modified", "action": "DOM edited", "timestamp": "2025-01-29T10:53:46.327Z", "user": "Marina Gallardo", "report": "reports/2025-W05_2025-01-27_2025-02-02.html", "period": "Jan 27 \u2013 Feb 2, 2025", "week": "2025-W05"}, {"entity": "Nannychex is SurePayroll by Paychex", "entity_type": "page", "event": "page_dom_modified", "action": "DOM edited", "timestamp": "2025-01-29T10:52:36.209Z", "user": "Marina Gallardo", "report": "reports/2025-W05_2025-01-27_2025-02-02.html", "period": "Jan 27 \u2013 Feb 2, 2025", "week": "2025-W05"}, {"entity": "Home", "entity_type": "page", "event": "page_dom_modified", "action": "DOM edited", "timestamp": "2025-01-29T10:42:39.187Z", "user": "Marina Gallardo", "report": "reports/2025-W05_2025-01-27_2025-02-02.html", "period": "Jan 27 \u2013 Feb 2, 2025", "week": "2025-W05"}, {"entity": "Home", "entity_type": "page", "event": "page_dom_modified", "action": "DOM edited", "timestamp": "2025-01-29T10:34:59.937Z", "user": "Marina Gallardo", "report": "reports/2025-W05_2025-01-27_2025-02-02.html", "period": "Jan 27 \u2013 Feb 2, 2025", "week": "2025-W05"}, {"entity": "Home", "entity_type": "page", "event": "page_dom_modified", "action": "DOM edited", "timestamp": "2025-01-29T10:22:22.546Z", "user": "Marina Gallardo", "report": "reports/2025-W05_2025-01-27_2025-02-02.html", "period": "Jan 27 \u2013 Feb 2, 2025", "week": "2025-W05"}, {"entity": "Calculator Template", "entity_type": "page", "event": "page_dom_modified", "action": "DOM edited", "timestamp": "2025-01-28T18:24:06.369Z", "user": "Dustin Solmonson", "report": "reports/2025-W05_2025-01-27_2025-02-02.html", "period": "Jan 27 \u2013 Feb 2, 2025", "week": "2025-W05"}, {"entity": "Roth vs Traditional 401k Calculator", "entity_type": "page", "event": "page_dom_modified", "action": "DOM edited", "timestamp": "2025-01-28T17:15:21.418Z", "user": "Dustin Solmonson", "report": "reports/2025-W05_2025-01-27_2025-02-02.html", "period": "Jan 27 \u2013 Feb 2, 2025", "week": "2025-W05"}, {"entity": "Asset Allocation Calculator", "entity_type": "page", "event": "page_dom_modified", "action": "DOM edited", "timestamp": "2025-01-28T17:14:52.178Z", "user": "Dustin Solmonson", "report": "reports/2025-W05_2025-01-27_2025-02-02.html", "period": "Jan 27 \u2013 Feb 2, 2025", "week": "2025-W05"}, {"entity": "Lease vs Buy Calculator", "entity_type": "page", "event": "page_dom_modified", "action": "DOM edited", "timestamp": "2025-01-28T17:12:55.057Z", "user": "Dustin Solmonson", "report": "reports/2025-W05_2025-01-27_2025-02-02.html", "period": "Jan 27 \u2013 Feb 2, 2025", "week": "2025-W05"}, {"entity": "Cash Flow Calculator", "entity_type": "page", "event": "page_dom_modified", "action": "DOM edited", "timestamp": "2025-01-28T17:10:14.910Z", "user": "Dustin Solmonson", "report": "reports/2025-W05_2025-01-27_2025-02-02.html", "period": "Jan 27 \u2013 Feb 2, 2025", "week": "2025-W05"}, {"entity": "Earned Income Credit Calculator", "entity_type": "page", "event": "page_dom_modified", "action": "DOM edited", "timestamp": "2025-01-28T17:09:38.451Z", "user": "Dustin Solmonson", "report": "reports/2025-W05_2025-01-27_2025-02-02.html", "period": "Jan 27 \u2013 Feb 2, 2025", "week": "2025-W05"}, {"entity": "Gross Up Payroll Calculator", "entity_type": "page", "event": "page_dom_modified", "action": "DOM edited", "timestamp": "2025-01-28T17:08:20.106Z", "user": "Dustin Solmonson", "report": "reports/2025-W05_2025-01-27_2025-02-02.html", "period": "Jan 27 \u2013 Feb 2, 2025", "week": "2025-W05"}, {"entity": "Salary Paycheck Calculator", "entity_type": "page", "event": "page_dom_modified", "action": "DOM edited", "timestamp": "2025-01-28T17:07:35.515Z", "user": "Dustin Solmonson", "report": "reports/2025-W05_2025-01-27_2025-02-02.html", "period": "Jan 27 \u2013 Feb 2, 2025", "week": "2025-W05"}, {"entity": "Self Employment Tax Calculator", "entity_type": "page", "event": "page_dom_modified", "action": "DOM edited", "timestamp": "2025-01-28T17:06:46.018Z", "user": "Dustin Solmonson", "report": "reports/2025-W05_2025-01-27_2025-02-02.html", "period": "Jan 27 \u2013 Feb 2, 2025", "week": "2025-W05"}, {"entity": "Flexible Spending Account Calculator", "entity_type": "page", "event": "page_dom_modified", "action": "DOM edited", "timestamp": "2025-01-28T17:05:56.704Z", "user": "Dustin Solmonson", "report": "reports/2025-W05_2025-01-27_2025-02-02.html", "period": "Jan 27 \u2013 Feb 2, 2025", "week": "2025-W05"}, {"entity": "Estimate Employee Payroll with Our Hourly Paycheck Calculator", "entity_type": "page", "event": "page_dom_modified", "action": "DOM edited", "timestamp": "2025-01-28T17:04:25.044Z", "user": "Dustin Solmonson", "report": "reports/2025-W05_2025-01-27_2025-02-02.html", "period": "Jan 27 \u2013 Feb 2, 2025", "week": "2025-W05"}, {"entity": "Get Started", "entity_type": "page", "event": "page_dom_modified", "action": "DOM edited", "timestamp": "2025-01-28T16:51:40.587Z", "user": "Marina Gallardo", "report": "reports/2025-W05_2025-01-27_2025-02-02.html", "period": "Jan 27 \u2013 Feb 2, 2025", "week": "2025-W05"}, {"entity": "Get Started", "entity_type": "page", "event": "page_dom_modified", "action": "DOM edited", "timestamp": "2025-01-28T15:46:09.879Z", "user": "Marina Gallardo", "report": "reports/2025-W05_2025-01-27_2025-02-02.html", "period": "Jan 27 \u2013 Feb 2, 2025", "week": "2025-W05"}, {"entity": "body", "entity_type": "page", "event": "page_settings_custom_code_modified", "action": "Custom code edited", "timestamp": "2025-01-28T15:09:13.678Z", "user": "Marina Gallardo", "report": "reports/2025-W05_2025-01-27_2025-02-02.html", "period": "Jan 27 \u2013 Feb 2, 2025", "week": "2025-W05"}, {"entity": "body", "entity_type": "page", "event": "page_settings_custom_code_modified", "action": "Custom code edited", "timestamp": "2025-01-28T15:06:04.704Z", "user": "Marina Gallardo", "report": "reports/2025-W05_2025-01-27_2025-02-02.html", "period": "Jan 27 \u2013 Feb 2, 2025", "week": "2025-W05"}, {"entity": "Get Started", "entity_type": "page", "event": "page_dom_modified", "action": "DOM edited", "timestamp": "2025-01-28T12:25:33.119Z", "user": "Marina Gallardo", "report": "reports/2025-W05_2025-01-27_2025-02-02.html", "period": "Jan 27 \u2013 Feb 2, 2025", "week": "2025-W05"}, {"entity": "Get Started", "entity_type": "page", "event": "page_dom_modified", "action": "DOM edited", "timestamp": "2025-01-28T11:18:21.915Z", "user": "Marina Gallardo", "report": "reports/2025-W05_2025-01-27_2025-02-02.html", "period": "Jan 27 \u2013 Feb 2, 2025", "week": "2025-W05"}, {"entity": "Get Started", "entity_type": "page", "event": "page_dom_modified", "action": "DOM edited", "timestamp": "2025-01-28T10:44:38.006Z", "user": "Marina Gallardo", "report": "reports/2025-W05_2025-01-27_2025-02-02.html", "period": "Jan 27 \u2013 Feb 2, 2025", "week": "2025-W05"}, {"entity": "Get Started", "entity_type": "page", "event": "page_dom_modified", "action": "DOM edited", "timestamp": "2025-01-28T10:36:34.073Z", "user": "Marina Gallardo", "report": "reports/2025-W05_2025-01-27_2025-02-02.html", "period": "Jan 27 \u2013 Feb 2, 2025", "week": "2025-W05"}, {"entity": "Get Started", "entity_type": "page", "event": "page_dom_modified", "action": "DOM edited", "timestamp": "2025-01-28T10:25:37.194Z", "user": "Marina Gallardo", "report": "reports/2025-W05_2025-01-27_2025-02-02.html", "period": "Jan 27 \u2013 Feb 2, 2025", "week": "2025-W05"}, {"entity": "W9 Form: Definition & How to Fill it Out ", "entity_type": "article", "event": "cms_item", "action": "Modified", "timestamp": "2025-01-27T21:45:23.491Z", "user": "System", "report": "reports/2025-W05_2025-01-27_2025-02-02.html", "period": "Jan 27 \u2013 Feb 2, 2025", "week": "2025-W05"}, {"entity": "W9 Form: Definition & How to Fill it Out ", "entity_type": "article", "event": "cms_item", "action": "Created", "timestamp": "2025-01-27T21:43:10.736Z", "user": "System", "report": "reports/2025-W05_2025-01-27_2025-02-02.html", "period": "Jan 27 \u2013 Feb 2, 2025", "week": "2025-W05"}, {"entity": "Default Payroll vs Auto Payroll: Which is Right for You? ", "entity_type": "article", "event": "cms_item", "action": "Modified", "timestamp": "2025-01-27T21:28:01.627Z", "user": "System", "report": "reports/2025-W05_2025-01-27_2025-02-02.html", "period": "Jan 27 \u2013 Feb 2, 2025", "week": "2025-W05"}, {"entity": "State Reciprocity: When Where You Live Isn\u2019t Where You Work  ", "entity_type": "article", "event": "cms_item", "action": "Modified", "timestamp": "2025-01-27T21:24:20.710Z", "user": "System", "report": "reports/2025-W05_2025-01-27_2025-02-02.html", "period": "Jan 27 \u2013 Feb 2, 2025", "week": "2025-W05"}, {"entity": "Default Payroll vs Auto Payroll: Which is Right for You? ", "entity_type": "article", "event": "cms_item", "action": "Modified", "timestamp": "2025-01-27T21:07:40.226Z", "user": "System", "report": "reports/2025-W05_2025-01-27_2025-02-02.html", "period": "Jan 27 \u2013 Feb 2, 2025", "week": "2025-W05"}, {"entity": "State Reciprocity: When Where You Live Isn\u2019t Where You Work  ", "entity_type": "article", "event": "cms_item", "action": "Modified", "timestamp": "2025-01-27T21:05:51.989Z", "user": "System", "report": "reports/2025-W05_2025-01-27_2025-02-02.html", "period": "Jan 27 \u2013 Feb 2, 2025", "week": "2025-W05"}, {"entity": "Default Payroll vs Auto Payroll: Which is Right for You? ", "entity_type": "article", "event": "cms_item", "action": "Modified", "timestamp": "2025-01-27T20:35:01.330Z", "user": "System", "report": "reports/2025-W05_2025-01-27_2025-02-02.html", "period": "Jan 27 \u2013 Feb 2, 2025", "week": "2025-W05"}, {"entity": "How to Issue a Final Paycheck", "entity_type": "article", "event": "cms_item", "action": "Modified", "timestamp": "2025-01-27T20:07:54.233Z", "user": "System", "report": "reports/2025-W05_2025-01-27_2025-02-02.html", "period": "Jan 27 \u2013 Feb 2, 2025", "week": "2025-W05"}, {"entity": "10 Types of Time Off", "entity_type": "article", "event": "cms_item", "action": "Modified", "timestamp": "2025-01-27T19:25:29.886Z", "user": "System", "report": "reports/2025-W05_2025-01-27_2025-02-02.html", "period": "Jan 27 \u2013 Feb 2, 2025", "week": "2025-W05"}, {"entity": "10 Types of Time Off", "entity_type": "article", "event": "cms_item", "action": "Modified", "timestamp": "2025-01-27T19:23:13.561Z", "user": "System", "report": "reports/2025-W05_2025-01-27_2025-02-02.html", "period": "Jan 27 \u2013 Feb 2, 2025", "week": "2025-W05"}, {"entity": "Navigating Health Insurance Options for Self-Employed ", "entity_type": "article", "event": "cms_item", "action": "Modified", "timestamp": "2025-01-27T19:16:11.231Z", "user": "System", "report": "reports/2025-W05_2025-01-27_2025-02-02.html", "period": "Jan 27 \u2013 Feb 2, 2025", "week": "2025-W05"}, {"entity": "Navigating Health Insurance Options for Self-Employed ", "entity_type": "article", "event": "cms_item", "action": "Modified", "timestamp": "2025-01-27T19:14:11.588Z", "user": "System", "report": "reports/2025-W05_2025-01-27_2025-02-02.html", "period": "Jan 27 \u2013 Feb 2, 2025", "week": "2025-W05"}, {"entity": "Understanding FSA, HSA, and HRA Benefits for Your Small Business ", "entity_type": "article", "event": "cms_item", "action": "Modified", "timestamp": "2025-01-27T19:07:06.946Z", "user": "System", "report": "reports/2025-W05_2025-01-27_2025-02-02.html", "period": "Jan 27 \u2013 Feb 2, 2025", "week": "2025-W05"}, {"entity": "Understanding FSA, HSA, and HRA Benefits for Your Small Business ", "entity_type": "article", "event": "cms_item", "action": "Modified", "timestamp": "2025-01-27T19:04:52.235Z", "user": "System", "report": "reports/2025-W05_2025-01-27_2025-02-02.html", "period": "Jan 27 \u2013 Feb 2, 2025", "week": "2025-W05"}, {"entity": "How to Create a Paid Time Off Policy", "entity_type": "article", "event": "cms_item", "action": "Modified", "timestamp": "2025-01-27T18:53:47.598Z", "user": "System", "report": "reports/2025-W05_2025-01-27_2025-02-02.html", "period": "Jan 27 \u2013 Feb 2, 2025", "week": "2025-W05"}, {"entity": "How to Create a Paid Time Off Policy", "entity_type": "article", "event": "cms_item", "action": "Modified", "timestamp": "2025-01-27T18:51:55.048Z", "user": "System", "report": "reports/2025-W05_2025-01-27_2025-02-02.html", "period": "Jan 27 \u2013 Feb 2, 2025", "week": "2025-W05"}, {"entity": "How to Create a Paid Time Off Policy", "entity_type": "article", "event": "cms_item", "action": "Modified", "timestamp": "2025-01-27T18:50:22.978Z", "user": "System", "report": "reports/2025-W05_2025-01-27_2025-02-02.html", "period": "Jan 27 \u2013 Feb 2, 2025", "week": "2025-W05"}, {"entity": "How to Create a Paid Time Off Policy", "entity_type": "article", "event": "cms_item", "action": "Modified", "timestamp": "2025-01-27T18:48:28.354Z", "user": "System", "report": "reports/2025-W05_2025-01-27_2025-02-02.html", "period": "Jan 27 \u2013 Feb 2, 2025", "week": "2025-W05"}, {"entity": "Payroll Tax Calculator", "entity_type": "page", "event": "page_dom_modified", "action": "DOM edited", "timestamp": "2025-01-27T18:41:16.054Z", "user": "Dustin Solmonson", "report": "reports/2025-W05_2025-01-27_2025-02-02.html", "period": "Jan 27 \u2013 Feb 2, 2025", "week": "2025-W05"}, {"entity": "Marginal Tax Rate Calculator", "entity_type": "page", "event": "page_dom_modified", "action": "DOM edited", "timestamp": "2025-01-27T18:40:49.863Z", "user": "Dustin Solmonson", "report": "reports/2025-W05_2025-01-27_2025-02-02.html", "period": "Jan 27 \u2013 Feb 2, 2025", "week": "2025-W05"}, {"entity": "Marginal Tax Rate Calculator", "entity_type": "page", "event": "page_dom_modified", "action": "DOM edited", "timestamp": "2025-01-27T18:30:03.179Z", "user": "Dustin Solmonson", "report": "reports/2025-W05_2025-01-27_2025-02-02.html", "period": "Jan 27 \u2013 Feb 2, 2025", "week": "2025-W05"}, {"entity": "Payroll", "entity_type": "page", "event": "page_dom_modified", "action": "DOM edited", "timestamp": "2025-01-27T18:21:35.529Z", "user": "Dustin Solmonson", "report": "reports/2025-W05_2025-01-27_2025-02-02.html", "period": "Jan 27 \u2013 Feb 2, 2025", "week": "2025-W05"}, {"entity": "Payroll", "entity_type": "page", "event": "page_dom_modified", "action": "DOM edited", "timestamp": "2025-01-27T17:28:45.136Z", "user": "Dustin Solmonson", "report": "reports/2025-W05_2025-01-27_2025-02-02.html", "period": "Jan 27 \u2013 Feb 2, 2025", "week": "2025-W05"}, {"entity": "Articles Template", "entity_type": "page", "event": "page_dom_modified", "action": "DOM edited", "timestamp": "2025-01-27T17:11:30.360Z", "user": "Dustin Solmonson", "report": "reports/2025-W05_2025-01-27_2025-02-02.html", "period": "Jan 27 \u2013 Feb 2, 2025", "week": "2025-W05"}, {"entity": "Get Started", "entity_type": "page", "event": "page_dom_modified", "action": "DOM edited", "timestamp": "2025-01-27T16:25:25.732Z", "user": "Marina Gallardo", "report": "reports/2025-W05_2025-01-27_2025-02-02.html", "period": "Jan 27 \u2013 Feb 2, 2025", "week": "2025-W05"}, {"entity": "SureHR", "entity_type": "page", "event": "page_dom_modified", "action": "DOM edited", "timestamp": "2025-01-27T16:31:02.510Z", "user": "Michael Rosenthal", "report": "reports/2025-W05_2025-01-27_2025-02-02.html", "period": "Jan 27 \u2013 Feb 2, 2025", "week": "2025-W05"}, {"entity": "Get Started", "entity_type": "page", "event": "page_dom_modified", "action": "DOM edited", "timestamp": "2025-01-27T16:13:53.976Z", "user": "Marina Gallardo", "report": "reports/2025-W05_2025-01-27_2025-02-02.html", "period": "Jan 27 \u2013 Feb 2, 2025", "week": "2025-W05"}, {"entity": "Get Started", "entity_type": "page", "event": "page_dom_modified", "action": "DOM edited", "timestamp": "2025-01-27T11:57:16.303Z", "user": "Marina Gallardo", "report": "reports/2025-W05_2025-01-27_2025-02-02.html", "period": "Jan 27 \u2013 Feb 2, 2025", "week": "2025-W05"}, {"entity": "Get Started", "entity_type": "page", "event": "page_dom_modified", "action": "DOM edited", "timestamp": "2025-01-27T11:50:39.447Z", "user": "Marina Gallardo", "report": "reports/2025-W05_2025-01-27_2025-02-02.html", "period": "Jan 27 \u2013 Feb 2, 2025", "week": "2025-W05"}, {"entity": "How to Issue a Final Paycheck", "entity_type": "article", "event": "cms_item", "action": "Modified", "timestamp": "2025-01-27T09:47:48.555Z", "user": "System", "report": "reports/2025-W05_2025-01-27_2025-02-02.html", "period": "Jan 27 \u2013 Feb 2, 2025", "week": "2025-W05"}, {"entity": "How to Issue a Final Paycheck", "entity_type": "article", "event": "cms_item", "action": "Modified", "timestamp": "2025-01-27T09:46:02.282Z", "user": "System", "report": "reports/2025-W05_2025-01-27_2025-02-02.html", "period": "Jan 27 \u2013 Feb 2, 2025", "week": "2025-W05"}]