[{"entity": "How to Issue a Final Paycheck", "entity_type": "article", "event": "cms_item", "action": "Modified", "timestamp": "2025-01-24T22:29:27.832Z", "user": "System", "report": "reports/2025-W04_2025-01-20_2025-01-26.html", "period": "Jan 20 \u2013 Jan 26, 2025", "week": "2025-W04"}, {"entity": "Pricing", "entity_type": "page", "event": "page_dom_modified", "action": "DOM edited", "timestamp": "2025-01-24T20:57:19.954Z", "user": "Sean Connelly", "report": "reports/2025-W04_2025-01-20_2025-01-26.html", "period": "Jan 20 \u2013 Jan 26, 2025", "week": "2025-W04"}, {"entity": "SureHR", "entity_type": "page", "event": "page_dom_modified", "action": "DOM edited", "timestamp": "2025-01-24T20:09:54.718Z", "user": "Michael Rosenthal", "report": "reports/2025-W04_2025-01-20_2025-01-26.html", "period": "Jan 20 \u2013 Jan 26, 2025", "week": "2025-W04"}, {"entity": "SureHR", "entity_type": "page", "event": "page_dom_modified", "action": "DOM edited", "timestamp": "2025-01-24T20:03:31.359Z", "user": "Michael Rosenthal", "report": "reports/2025-W04_2025-01-20_2025-01-26.html", "period": "Jan 20 \u2013 Jan 26, 2025", "week": "2025-W04"}, {"entity": "SureHR", "entity_type": "page", "event": "page_dom_modified", "action": "DOM edited", "timestamp": "2025-01-24T19:48:33.882Z", "user": "Michael Rosenthal", "report": "reports/2025-W04_2025-01-20_2025-01-26.html", "period": "Jan 20 \u2013 Jan 26, 2025", "week": "2025-W04"}, {"entity": "SureHR", "entity_type": "page", "event": "page_dom_modified", "action": "DOM edited", "timestamp": "2025-01-24T19:07:30.366Z", "user": "Michael Rosenthal", "report": "reports/2025-W04_2025-01-20_2025-01-26.html", "period": "Jan 20 \u2013 Jan 26, 2025", "week": "2025-W04"}, {"entity": "SureHR", "entity_type": "page", "event": "page_dom_modified", "action": "DOM edited", "timestamp": "2025-01-24T18:59:22.662Z", "user": "Michael Rosenthal", "report": "reports/2025-W04_2025-01-20_2025-01-26.html", "period": "Jan 20 \u2013 Jan 26, 2025", "week": "2025-W04"}, {"entity": "Direct Deposit", "entity_type": "article", "event": "cms_item", "action": "Modified", "timestamp": "2025-01-24T16:09:56.760Z", "user": "System", "report": "reports/2025-W04_2025-01-20_2025-01-26.html", "period": "Jan 20 \u2013 Jan 26, 2025", "week": "2025-W04"}, {"entity": "SureHR", "entity_type": "page", "event": "page_dom_modified", "action": "DOM edited", "timestamp": "2025-01-24T14:55:45.579Z", "user": "Michael Rosenthal", "report": "reports/2025-W04_2025-01-20_2025-01-26.html", "period": "Jan 20 \u2013 Jan 26, 2025", "week": "2025-W04"}, {"entity": "What is a Nanny Share?", "entity_type": "article", "event": "cms_item", "action": "Modified", "timestamp": "2025-01-24T14:16:21.401Z", "user": "System", "report": "reports/2025-W04_2025-01-20_2025-01-26.html", "period": "Jan 20 \u2013 Jan 26, 2025", "week": "2025-W04"}, {"entity": "What is a Nanny Share?", "entity_type": "article", "event": "cms_item", "action": "Modified", "timestamp": "2025-01-24T14:13:50.193Z", "user": "System", "report": "reports/2025-W04_2025-01-20_2025-01-26.html", "period": "Jan 20 \u2013 Jan 26, 2025", "week": "2025-W04"}, {"entity": "Pricing", "entity_type": "page", "event": "page_dom_modified", "action": "DOM edited", "timestamp": "2025-01-24T14:00:44.939Z", "user": "Sean Connelly", "report": "reports/2025-W04_2025-01-20_2025-01-26.html", "period": "Jan 20 \u2013 Jan 26, 2025", "week": "2025-W04"}, {"entity": "How do I get an EIN Number?", "entity_type": "article", "event": "cms_item", "action": "Modified", "timestamp": "2025-01-24T13:32:10.136Z", "user": "System", "report": "reports/2025-W04_2025-01-20_2025-01-26.html", "period": "Jan 20 \u2013 Jan 26, 2025", "week": "2025-W04"}, {"entity": "How do I get an EIN Number?", "entity_type": "article", "event": "cms_item", "action": "Modified", "timestamp": "2025-01-24T13:30:28.907Z", "user": "System", "report": "reports/2025-W04_2025-01-20_2025-01-26.html", "period": "Jan 20 \u2013 Jan 26, 2025", "week": "2025-W04"}, {"entity": "How to Issue a Final Paycheck", "entity_type": "article", "event": "cms_item", "action": "Created", "timestamp": "2025-01-24T12:40:57.226Z", "user": "System", "report": "reports/2025-W04_2025-01-20_2025-01-26.html", "period": "Jan 20 \u2013 Jan 26, 2025", "week": "2025-W04"}, {"entity": "Direct Deposit", "entity_type": "article", "event": "cms_item", "action": "Created", "timestamp": "2025-01-24T12:39:59.689Z", "user": "System", "report": "reports/2025-W04_2025-01-20_2025-01-26.html", "period": "Jan 20 \u2013 Jan 26, 2025", "week": "2025-W04"}, {"entity": "Small Business Time Off Guide", "entity_type": "article", "event": "cms_item", "action": "Created", "timestamp": "2025-01-24T12:37:38.865Z", "user": "System", "report": "reports/2025-W04_2025-01-20_2025-01-26.html", "period": "Jan 20 \u2013 Jan 26, 2025", "week": "2025-W04"}, {"entity": "What is a Nanny Share?", "entity_type": "article", "event": "cms_item", "action": "Created", "timestamp": "2025-01-24T12:34:28.942Z", "user": "System", "report": "reports/2025-W04_2025-01-20_2025-01-26.html", "period": "Jan 20 \u2013 Jan 26, 2025", "week": "2025-W04"}, {"entity": "How do I get an EIN Number?", "entity_type": "article", "event": "cms_item", "action": "Created", "timestamp": "2025-01-24T12:31:55.736Z", "user": "System", "report": "reports/2025-W04_2025-01-20_2025-01-26.html", "period": "Jan 20 \u2013 Jan 26, 2025", "week": "2025-W04"}, {"entity": "How to Choose Between FSA's, HSAs and HRAs", "entity_type": "article", "event": "cms_item", "action": "Created", "timestamp": "2025-01-24T12:30:01.673Z", "user": "System", "report": "reports/2025-W04_2025-01-20_2025-01-26.html", "period": "Jan 20 \u2013 Jan 26, 2025", "week": "2025-W04"}, {"entity": "How to Create a Paid Time Off Policy", "entity_type": "article", "event": "cms_item", "action": "Created", "timestamp": "2025-01-24T12:28:05.650Z", "user": "System", "report": "reports/2025-W04_2025-01-20_2025-01-26.html", "period": "Jan 20 \u2013 Jan 26, 2025", "week": "2025-W04"}, {"entity": "SureHR", "entity_type": "page", "event": "page_dom_modified", "action": "DOM edited", "timestamp": "2025-01-23T20:24:14.093Z", "user": "Michael Rosenthal", "report": "reports/2025-W04_2025-01-20_2025-01-26.html", "period": "Jan 20 \u2013 Jan 26, 2025", "week": "2025-W04"}, {"entity": "SureHR", "entity_type": "page", "event": "page_dom_modified", "action": "DOM edited", "timestamp": "2025-01-23T20:18:37.864Z", "user": "Michael Rosenthal", "report": "reports/2025-W04_2025-01-20_2025-01-26.html", "period": "Jan 20 \u2013 Jan 26, 2025", "week": "2025-W04"}, {"entity": "SureHR", "entity_type": "page", "event": "page_dom_modified", "action": "DOM edited", "timestamp": "2025-01-23T19:44:54.674Z", "user": "Michael Rosenthal", "report": "reports/2025-W04_2025-01-20_2025-01-26.html", "period": "Jan 20 \u2013 Jan 26, 2025", "week": "2025-W04"}, {"entity": "SureHR", "entity_type": "page", "event": "page_dom_modified", "action": "DOM edited", "timestamp": "2025-01-23T19:36:18.261Z", "user": "Michael Rosenthal", "report": "reports/2025-W04_2025-01-20_2025-01-26.html", "period": "Jan 20 \u2013 Jan 26, 2025", "week": "2025-W04"}, {"entity": "SureHR", "entity_type": "page", "event": "page_dom_modified", "action": "DOM edited", "timestamp": "2025-01-23T19:19:18.619Z", "user": "Michael Rosenthal", "report": "reports/2025-W04_2025-01-20_2025-01-26.html", "period": "Jan 20 \u2013 Jan 26, 2025", "week": "2025-W04"}, {"entity": "SureHR", "entity_type": "page", "event": "page_dom_modified", "action": "DOM edited", "timestamp": "2025-01-23T17:50:32.546Z", "user": "Michael Rosenthal", "report": "reports/2025-W04_2025-01-20_2025-01-26.html", "period": "Jan 20 \u2013 Jan 26, 2025", "week": "2025-W04"}, {"entity": "SureHR", "entity_type": "page", "event": "page_dom_modified", "action": "DOM edited", "timestamp": "2025-01-23T17:27:04.589Z", "user": "Michael Rosenthal", "report": "reports/2025-W04_2025-01-20_2025-01-26.html", "period": "Jan 20 \u2013 Jan 26, 2025", "week": "2025-W04"}, {"entity": "SureHR", "entity_type": "page", "event": "page_dom_modified", "action": "DOM edited", "timestamp": "2025-01-23T16:34:23.821Z", "user": "Michael Rosenthal", "report": "reports/2025-W04_2025-01-20_2025-01-26.html", "period": "Jan 20 \u2013 Jan 26, 2025", "week": "2025-W04"}, {"entity": "SureHR", "entity_type": "page", "event": "page_dom_modified", "action": "DOM edited", "timestamp": "2025-01-23T15:49:02.805Z", "user": "Michael Rosenthal", "report": "reports/2025-W04_2025-01-20_2025-01-26.html", "period": "Jan 20 \u2013 Jan 26, 2025", "week": "2025-W04"}, {"entity": "SureHR", "entity_type": "page", "event": "page_dom_modified", "action": "DOM edited", "timestamp": "2025-01-23T13:21:39.992Z", "user": "Michael Rosenthal", "report": "reports/2025-W04_2025-01-20_2025-01-26.html", "period": "Jan 20 \u2013 Jan 26, 2025", "week": "2025-W04"}, {"entity": "SureHR", "entity_type": "page", "event": "page_dom_modified", "action": "DOM edited", "timestamp": "2025-01-23T13:12:11.385Z", "user": "Michael Rosenthal", "report": "reports/2025-W04_2025-01-20_2025-01-26.html", "period": "Jan 20 \u2013 Jan 26, 2025", "week": "2025-W04"}, {"entity": "SureHR", "entity_type": "page", "event": "page_dom_modified", "action": "DOM edited", "timestamp": "2025-01-22T21:20:41.760Z", "user": "Michael Rosenthal", "report": "reports/2025-W04_2025-01-20_2025-01-26.html", "period": "Jan 20 \u2013 Jan 26, 2025", "week": "2025-W04"}, {"entity": "Delaware", "entity_type": "article", "event": "cms_item", "action": "Published", "timestamp": "2025-01-22T19:26:23.375Z", "user": "Akimbo Studio", "report": "reports/2025-W04_2025-01-20_2025-01-26.html", "period": "Jan 20 \u2013 Jan 26, 2025", "week": "2025-W04"}, {"entity": "Delaware", "entity_type": "article", "event": "cms_item", "action": "Modified", "timestamp": "2025-01-22T19:26:16.285Z", "user": "Akimbo Studio", "report": "reports/2025-W04_2025-01-20_2025-01-26.html", "period": "Jan 20 \u2013 Jan 26, 2025", "week": "2025-W04"}, {"entity": "Puerto Rico", "entity_type": "article", "event": "cms_item", "action": "Published", "timestamp": "2025-01-22T19:23:53.923Z", "user": "Akimbo Studio", "report": "reports/2025-W04_2025-01-20_2025-01-26.html", "period": "Jan 20 \u2013 Jan 26, 2025", "week": "2025-W04"}, {"entity": "Puerto Rico", "entity_type": "article", "event": "cms_item", "action": "Modified", "timestamp": "2025-01-22T19:23:27.387Z", "user": "Akimbo Studio", "report": "reports/2025-W04_2025-01-20_2025-01-26.html", "period": "Jan 20 \u2013 Jan 26, 2025", "week": "2025-W04"}, {"entity": "Puerto Rico", "entity_type": "article", "event": "cms_item", "action": "Modified", "timestamp": "2025-01-22T19:18:53.349Z", "user": "Akimbo Studio", "report": "reports/2025-W04_2025-01-20_2025-01-26.html", "period": "Jan 20 \u2013 Jan 26, 2025", "week": "2025-W04"}, {"entity": "Puerto Rico", "entity_type": "article", "event": "cms_item", "action": "Modified", "timestamp": "2025-01-22T19:17:43.430Z", "user": "Akimbo Studio", "report": "reports/2025-W04_2025-01-20_2025-01-26.html", "period": "Jan 20 \u2013 Jan 26, 2025", "week": "2025-W04"}, {"entity": "Puerto Rico", "entity_type": "article", "event": "cms_item", "action": "Modified", "timestamp": "2025-01-22T19:15:28.202Z", "user": "Akimbo Studio", "report": "reports/2025-W04_2025-01-20_2025-01-26.html", "period": "Jan 20 \u2013 Jan 26, 2025", "week": "2025-W04"}, {"entity": "Puerto Rico", "entity_type": "article", "event": "cms_item", "action": "Modified", "timestamp": "2025-01-22T19:12:53.715Z", "user": "Akimbo Studio", "report": "reports/2025-W04_2025-01-20_2025-01-26.html", "period": "Jan 20 \u2013 Jan 26, 2025", "week": "2025-W04"}, {"entity": "Puerto Rico", "entity_type": "article", "event": "cms_item", "action": "Modified", "timestamp": "2025-01-22T19:11:17.923Z", "user": "Akimbo Studio", "report": "reports/2025-W04_2025-01-20_2025-01-26.html", "period": "Jan 20 \u2013 Jan 26, 2025", "week": "2025-W04"}, {"entity": "Puerto Rico", "entity_type": "article", "event": "cms_item", "action": "Modified", "timestamp": "2025-01-22T18:57:47.545Z", "user": "Akimbo Studio", "report": "reports/2025-W04_2025-01-20_2025-01-26.html", "period": "Jan 20 \u2013 Jan 26, 2025", "week": "2025-W04"}, {"entity": "Puerto Rico", "entity_type": "article", "event": "cms_item", "action": "Created", "timestamp": "2025-01-22T18:54:27.773Z", "user": "Akimbo Studio", "report": "reports/2025-W04_2025-01-20_2025-01-26.html", "period": "Jan 20 \u2013 Jan 26, 2025", "week": "2025-W04"}, {"entity": "Georgia", "entity_type": "article", "event": "cms_item", "action": "Published", "timestamp": "2025-01-22T18:51:46.725Z", "user": "Akimbo Studio", "report": "reports/2025-W04_2025-01-20_2025-01-26.html", "period": "Jan 20 \u2013 Jan 26, 2025", "week": "2025-W04"}, {"entity": "SureHR", "entity_type": "page", "event": "page_dom_modified", "action": "DOM edited", "timestamp": "2025-01-22T18:22:07.326Z", "user": "Michael Rosenthal", "report": "reports/2025-W04_2025-01-20_2025-01-26.html", "period": "Jan 20 \u2013 Jan 26, 2025", "week": "2025-W04"}, {"entity": "SureHR", "entity_type": "page", "event": "page_dom_modified", "action": "DOM edited", "timestamp": "2025-01-22T18:09:57.582Z", "user": "Michael Rosenthal", "report": "reports/2025-W04_2025-01-20_2025-01-26.html", "period": "Jan 20 \u2013 Jan 26, 2025", "week": "2025-W04"}, {"entity": "SureHR", "entity_type": "page", "event": "page_dom_modified", "action": "DOM edited", "timestamp": "2025-01-22T17:48:31.959Z", "user": "Michael Rosenthal", "report": "reports/2025-W04_2025-01-20_2025-01-26.html", "period": "Jan 20 \u2013 Jan 26, 2025", "week": "2025-W04"}, {"entity": "How Many Hours is Part-Time Work?  ", "entity_type": "article", "event": "cms_item", "action": "Modified", "timestamp": "2025-01-21T21:22:43.354Z", "user": "System", "report": "reports/2025-W04_2025-01-20_2025-01-26.html", "period": "Jan 20 \u2013 Jan 26, 2025", "week": "2025-W04"}, {"entity": "How Many Hours is Part-Time Work?  ", "entity_type": "article", "event": "cms_item", "action": "Modified", "timestamp": "2025-01-21T21:00:40.766Z", "user": "System", "report": "reports/2025-W04_2025-01-20_2025-01-26.html", "period": "Jan 20 \u2013 Jan 26, 2025", "week": "2025-W04"}, {"entity": "How Many Hours is Part-Time Work?  ", "entity_type": "article", "event": "cms_item", "action": "Created", "timestamp": "2025-01-21T20:56:44.853Z", "user": "System", "report": "reports/2025-W04_2025-01-20_2025-01-26.html", "period": "Jan 20 \u2013 Jan 26, 2025", "week": "2025-W04"}, {"entity": "Style Guide", "entity_type": "page", "event": "page_dom_modified", "action": "DOM edited", "timestamp": "2025-01-21T19:51:03.948Z", "user": "Dustin Solmonson", "report": "reports/2025-W04_2025-01-20_2025-01-26.html", "period": "Jan 20 \u2013 Jan 26, 2025", "week": "2025-W04"}, {"entity": "Pricing", "entity_type": "page", "event": "page_dom_modified", "action": "DOM edited", "timestamp": "2025-01-21T19:41:42.406Z", "user": "Dustin Solmonson", "report": "reports/2025-W04_2025-01-20_2025-01-26.html", "period": "Jan 20 \u2013 Jan 26, 2025", "week": "2025-W04"}, {"entity": "head", "entity_type": "page", "event": "page_settings_custom_code_modified", "action": "Custom code edited", "timestamp": "2025-01-21T19:38:32.820Z", "user": "Dustin Solmonson", "report": "reports/2025-W04_2025-01-20_2025-01-26.html", "period": "Jan 20 \u2013 Jan 26, 2025", "week": "2025-W04"}, {"entity": "head", "entity_type": "page", "event": "page_settings_custom_code_modified", "action": "Custom code edited", "timestamp": "2025-01-21T19:32:57.900Z", "user": "Dustin Solmonson", "report": "reports/2025-W04_2025-01-20_2025-01-26.html", "period": "Jan 20 \u2013 Jan 26, 2025", "week": "2025-W04"}, {"entity": "head", "entity_type": "page", "event": "page_settings_custom_code_modified", "action": "Custom code edited", "timestamp": "2025-01-21T19:28:17.378Z", "user": "Dustin Solmonson", "report": "reports/2025-W04_2025-01-20_2025-01-26.html", "period": "Jan 20 \u2013 Jan 26, 2025", "week": "2025-W04"}, {"entity": "Pricing", "entity_type": "page", "event": "page_dom_modified", "action": "DOM edited", "timestamp": "2025-01-21T19:27:10.099Z", "user": "Dustin Solmonson", "report": "reports/2025-W04_2025-01-20_2025-01-26.html", "period": "Jan 20 \u2013 Jan 26, 2025", "week": "2025-W04"}, {"entity": "Pricing", "entity_type": "page", "event": "page_dom_modified", "action": "DOM edited", "timestamp": "2025-01-21T18:46:44.287Z", "user": "Dustin Solmonson", "report": "reports/2025-W04_2025-01-20_2025-01-26.html", "period": "Jan 20 \u2013 Jan 26, 2025", "week": "2025-W04"}, {"entity": "Pricing", "entity_type": "page", "event": "page_dom_modified", "action": "DOM edited", "timestamp": "2025-01-21T18:00:14.331Z", "user": "Dustin Solmonson", "report": "reports/2025-W04_2025-01-20_2025-01-26.html", "period": "Jan 20 \u2013 Jan 26, 2025", "week": "2025-W04"}, {"entity": "Pricing", "entity_type": "page", "event": "page_dom_modified", "action": "DOM edited", "timestamp": "2025-01-21T17:22:47.382Z", "user": "Dustin Solmonson", "report": "reports/2025-W04_2025-01-20_2025-01-26.html", "period": "Jan 20 \u2013 Jan 26, 2025", "week": "2025-W04"}, {"entity": "Pricing", "entity_type": "page", "event": "page_dom_modified", "action": "DOM edited", "timestamp": "2025-01-21T16:12:25.296Z", "user": "Dustin Solmonson", "report": "reports/2025-W04_2025-01-20_2025-01-26.html", "period": "Jan 20 \u2013 Jan 26, 2025", "week": "2025-W04"}, {"entity": "Pricing", "entity_type": "page", "event": "page_dom_modified", "action": "DOM edited", "timestamp": "2025-01-21T15:57:06.080Z", "user": "Dustin Solmonson", "report": "reports/2025-W04_2025-01-20_2025-01-26.html", "period": "Jan 20 \u2013 Jan 26, 2025", "week": "2025-W04"}, {"entity": "How do Bank Holidays Affect Payday? ", "entity_type": "article", "event": "cms_item", "action": "Modified", "timestamp": "2025-01-21T14:46:57.997Z", "user": "System", "report": "reports/2025-W04_2025-01-20_2025-01-26.html", "period": "Jan 20 \u2013 Jan 26, 2025", "week": "2025-W04"}, {"entity": "Pricing", "entity_type": "page", "event": "page_dom_modified", "action": "DOM edited", "timestamp": "2025-01-21T14:39:02.385Z", "user": "Dustin Solmonson", "report": "reports/2025-W04_2025-01-20_2025-01-26.html", "period": "Jan 20 \u2013 Jan 26, 2025", "week": "2025-W04"}, {"entity": "SureHR", "entity_type": "page", "event": "page_dom_modified", "action": "DOM edited", "timestamp": "2025-01-21T12:52:04.767Z", "user": "Michael Rosenthal", "report": "reports/2025-W04_2025-01-20_2025-01-26.html", "period": "Jan 20 \u2013 Jan 26, 2025", "week": "2025-W04"}, {"entity": "SureHR", "entity_type": "page", "event": "page_dom_modified", "action": "DOM edited", "timestamp": "2025-01-21T12:35:08.299Z", "user": "Michael Rosenthal", "report": "reports/2025-W04_2025-01-20_2025-01-26.html", "period": "Jan 20 \u2013 Jan 26, 2025", "week": "2025-W04"}, {"entity": "Pricing", "entity_type": "page", "event": "page_dom_modified", "action": "DOM edited", "timestamp": "2025-01-20T22:31:00.851Z", "user": "Dustin Solmonson", "report": "reports/2025-W04_2025-01-20_2025-01-26.html", "period": "Jan 20 \u2013 Jan 26, 2025", "week": "2025-W04"}, {"entity": "Pricing", "entity_type": "page", "event": "page_dom_modified", "action": "DOM edited", "timestamp": "2025-01-20T22:18:25.630Z", "user": "Dustin Solmonson", "report": "reports/2025-W04_2025-01-20_2025-01-26.html", "period": "Jan 20 \u2013 Jan 26, 2025", "week": "2025-W04"}, {"entity": "SureHR", "entity_type": "page", "event": "page_dom_modified", "action": "DOM edited", "timestamp": "2025-01-20T20:39:55.224Z", "user": "Michael Rosenthal", "report": "reports/2025-W04_2025-01-20_2025-01-26.html", "period": "Jan 20 \u2013 Jan 26, 2025", "week": "2025-W04"}, {"entity": "Pricing", "entity_type": "page", "event": "page_dom_modified", "action": "DOM edited", "timestamp": "2025-01-20T20:34:08.718Z", "user": "Dustin Solmonson", "report": "reports/2025-W04_2025-01-20_2025-01-26.html", "period": "Jan 20 \u2013 Jan 26, 2025", "week": "2025-W04"}, {"entity": "Referral Terms & Conditions", "entity_type": "page", "event": "page_dom_modified", "action": "DOM edited", "timestamp": "2025-01-20T20:09:42.614Z", "user": "Sean Connelly", "report": "reports/2025-W04_2025-01-20_2025-01-26.html", "period": "Jan 20 \u2013 Jan 26, 2025", "week": "2025-W04"}, {"entity": "Pricing", "entity_type": "page", "event": "page_dom_modified", "action": "DOM edited", "timestamp": "2025-01-20T19:55:54.299Z", "user": "Dustin Solmonson", "report": "reports/2025-W04_2025-01-20_2025-01-26.html", "period": "Jan 20 \u2013 Jan 26, 2025", "week": "2025-W04"}, {"entity": "Pricing", "entity_type": "page", "event": "page_dom_modified", "action": "DOM edited", "timestamp": "2025-01-20T19:43:39.586Z", "user": "Dustin Solmonson", "report": "reports/2025-W04_2025-01-20_2025-01-26.html", "period": "Jan 20 \u2013 Jan 26, 2025", "week": "2025-W04"}, {"entity": "Pricing", "entity_type": "page", "event": "page_dom_modified", "action": "DOM edited", "timestamp": "2025-01-20T19:32:06.311Z", "user": "Dustin Solmonson", "report": "reports/2025-W04_2025-01-20_2025-01-26.html", "period": "Jan 20 \u2013 Jan 26, 2025", "week": "2025-W04"}, {"entity": "What Is a CP-575 Form?", "entity_type": "article", "event": "cms_item", "action": "Modified", "timestamp": "2025-01-20T18:50:07.911Z", "user": "System", "report": "reports/2025-W04_2025-01-20_2025-01-26.html", "period": "Jan 20 \u2013 Jan 26, 2025", "week": "2025-W04"}, {"entity": "Pricing", "entity_type": "page", "event": "page_dom_modified", "action": "DOM edited", "timestamp": "2025-01-20T17:57:54.037Z", "user": "Dustin Solmonson", "report": "reports/2025-W04_2025-01-20_2025-01-26.html", "period": "Jan 20 \u2013 Jan 26, 2025", "week": "2025-W04"}, {"entity": "What Is a CP-575 Form?", "entity_type": "article", "event": "cms_item", "action": "Modified", "timestamp": "2025-01-20T17:48:52.234Z", "user": "System", "report": "reports/2025-W04_2025-01-20_2025-01-26.html", "period": "Jan 20 \u2013 Jan 26, 2025", "week": "2025-W04"}, {"entity": "Is Your Small Business Required to File a BOI Report?", "entity_type": "article", "event": "cms_item", "action": "Modified", "timestamp": "2025-01-20T17:46:09.009Z", "user": "System", "report": "reports/2025-W04_2025-01-20_2025-01-26.html", "period": "Jan 20 \u2013 Jan 26, 2025", "week": "2025-W04"}, {"entity": "What Is a CP-575 Form?", "entity_type": "article", "event": "cms_item", "action": "Created", "timestamp": "2025-01-20T17:45:44.184Z", "user": "System", "report": "reports/2025-W04_2025-01-20_2025-01-26.html", "period": "Jan 20 \u2013 Jan 26, 2025", "week": "2025-W04"}, {"entity": "Pricing", "entity_type": "page", "event": "page_dom_modified", "action": "DOM edited", "timestamp": "2025-01-20T16:17:50.803Z", "user": "Dustin Solmonson", "report": "reports/2025-W04_2025-01-20_2025-01-26.html", "period": "Jan 20 \u2013 Jan 26, 2025", "week": "2025-W04"}, {"entity": "Pricing", "entity_type": "page", "event": "page_dom_modified", "action": "DOM edited", "timestamp": "2025-01-20T15:38:14.445Z", "user": "Dustin Solmonson", "report": "reports/2025-W04_2025-01-20_2025-01-26.html", "period": "Jan 20 \u2013 Jan 26, 2025", "week": "2025-W04"}, {"entity": "body", "entity_type": "page", "event": "page_settings_custom_code_modified", "action": "Custom code edited", "timestamp": "2025-01-20T15:33:57.981Z", "user": "Marina Gallardo", "report": "reports/2025-W04_2025-01-20_2025-01-26.html", "period": "Jan 20 \u2013 Jan 26, 2025", "week": "2025-W04"}, {"entity": "body", "entity_type": "page", "event": "page_settings_custom_code_modified", "action": "Custom code edited", "timestamp": "2025-01-20T15:32:04.537Z", "user": "Marina Gallardo", "report": "reports/2025-W04_2025-01-20_2025-01-26.html", "period": "Jan 20 \u2013 Jan 26, 2025", "week": "2025-W04"}, {"entity": "body", "entity_type": "page", "event": "page_settings_custom_code_modified", "action": "Custom code edited", "timestamp": "2025-01-20T15:25:41.016Z", "user": "Marina Gallardo", "report": "reports/2025-W04_2025-01-20_2025-01-26.html", "period": "Jan 20 \u2013 Jan 26, 2025", "week": "2025-W04"}, {"entity": "body", "entity_type": "page", "event": "page_settings_custom_code_modified", "action": "Custom code edited", "timestamp": "2025-01-20T15:24:27.126Z", "user": "Marina Gallardo", "report": "reports/2025-W04_2025-01-20_2025-01-26.html", "period": "Jan 20 \u2013 Jan 26, 2025", "week": "2025-W04"}, {"entity": "body", "entity_type": "page", "event": "page_settings_custom_code_modified", "action": "Custom code edited", "timestamp": "2025-01-20T15:23:44.728Z", "user": "Marina Gallardo", "report": "reports/2025-W04_2025-01-20_2025-01-26.html", "period": "Jan 20 \u2013 Jan 26, 2025", "week": "2025-W04"}, {"entity": "body", "entity_type": "page", "event": "page_settings_custom_code_modified", "action": "Custom code edited", "timestamp": "2025-01-20T15:22:33.420Z", "user": "Marina Gallardo", "report": "reports/2025-W04_2025-01-20_2025-01-26.html", "period": "Jan 20 \u2013 Jan 26, 2025", "week": "2025-W04"}, {"entity": "Referral Terms & Conditions", "entity_type": "page", "event": "page_dom_modified", "action": "DOM edited", "timestamp": "2025-01-20T15:19:59.265Z", "user": "Sean Connelly", "report": "reports/2025-W04_2025-01-20_2025-01-26.html", "period": "Jan 20 \u2013 Jan 26, 2025", "week": "2025-W04"}, {"entity": "Referral Terms & Conditions", "entity_type": "page", "event": "page_dom_modified", "action": "DOM edited", "timestamp": "2025-01-20T15:12:44.525Z", "user": "Sean Connelly", "report": "reports/2025-W04_2025-01-20_2025-01-26.html", "period": "Jan 20 \u2013 Jan 26, 2025", "week": "2025-W04"}, {"entity": "How to Do Payroll for One Employee: Simple Guide for 2025 ", "entity_type": "article", "event": "cms_item", "action": "Modified", "timestamp": "2025-01-20T12:58:36.166Z", "user": "System", "report": "reports/2025-W04_2025-01-20_2025-01-26.html", "period": "Jan 20 \u2013 Jan 26, 2025", "week": "2025-W04"}, {"entity": "What is a Bank Holiday: How Do Bank Holidays Affect Payday?", "entity_type": "article", "event": "cms_item", "action": "Modified", "timestamp": "2025-01-20T10:35:30.340Z", "user": "System", "report": "reports/2025-W04_2025-01-20_2025-01-26.html", "period": "Jan 20 \u2013 Jan 26, 2025", "week": "2025-W04"}]